dicttoxml.py
dicttoxml-1.7.15.dist-info/LICENCE.txt
dicttoxml-1.7.15.dist-info/METADATA
dicttoxml-1.7.15.dist-info/WHEEL
dicttoxml-1.7.15.dist-info/top_level.txt
dicttoxml-1.7.15.dist-info/RECORD
