Metadata-Version: 2.1
Name: dicttoxml
Version: 1.7.15
Summary: Converts a Python dictionary or other native data type into a valid XML string.
Home-page: https://github.com/quandyfactory/dicttoxml
Author: Ryan McGreal
Author-email: Ryan McGreal <ryan@quandyfactory.com>
License: GNU GENERAL PUBLIC LICENSE
Project-URL: Homepage, https://github.com/quandyfactory/dicttoxml
Platform: Cross-platform
Requires-Python: >=3.6
License-File: LICENCE.txt
